persistent_queue
